flake8_codeclimate.py
flake8_codeclimate-0.3.0.dist-info/METADATA
flake8_codeclimate-0.3.0.dist-info/RECORD
flake8_codeclimate-0.3.0.dist-info/WHEEL
flake8_codeclimate-0.3.0.dist-info/entry_points.txt
flake8_codeclimate-0.3.0.dist-info/top_level.txt
