Metadata-Version: 2.1
Name: flake8-codeclimate
Version: 0.3.0
Summary: Code Climate reporting formatter plugin for Flake8
Home-page: https://github.com/bennylope/flake8-codeclimate
Author: Ben Lopatin
Author-email: ben@benlopatin.com
License: MIT
Platform: UNKNOWN
Classifier: Framework :: Flake8
Classifier: Environment :: Console
Classifier: Intended Audience :: Developers
Classifier: License :: OSI Approved :: MIT License
Classifier: Programming Language :: Python
Classifier: Programming Language :: Python :: 2
Classifier: Programming Language :: Python :: 3
Classifier: Topic :: Software Development :: Libraries :: Python Modules
Classifier: Topic :: Software Development :: Quality Assurance
Requires-Dist: flake8 (>3.0.0)
